archABM/__init__.py
archABM/actions.py
archABM/aerosol_model.py
archABM/aerosol_model_colorado.py
archABM/aerosol_model_maxplanck.py
archABM/aerosol_model_mit.py
archABM/config.json
archABM/config.py
archABM/creator.py
archABM/database.py
archABM/engine.py
archABM/event.py
archABM/event_generator.py
archABM/event_model.py
archABM/options.py
archABM/parameters.py
archABM/person.py
archABM/place.py
archABM/results.py
archABM/schema.json
archABM/snapshot.py
archABM/snapshot_person.py
archABM/snapshot_place.py
archABM-0.4.1.dist-info/LICENSE
archABM-0.4.1.dist-info/METADATA
archABM-0.4.1.dist-info/WHEEL
archABM-0.4.1.dist-info/top_level.txt
archABM-0.4.1.dist-info/RECORD
