Metadata-Version: 2.1
Name: archABM
Version: 0.4.1
Summary: Agent based simulation for architectural spaces
Home-page: https://github.com/Vicomtech/ArchABM
Author: Vicomtech
Author-email: info@vicomtech.org
License: MIT license
Project-URL: Bug Reports, https://github.com/Vicomtech/ArchABM/issues
Project-URL: Documentation, https://vicomtech.github.io/ArchABM/
Project-URL: Source Code, https://github.com/Vicomtech/ArchABM
Keywords: agent simulation,architecture,building,workplace,discrete-event
Classifier: Development Status :: 2 - Pre-Alpha
Classifier: Intended Audience :: Developers
Classifier: License :: OSI Approved :: MIT License
Classifier: Natural Language :: English
Classifier: Programming Language :: Python :: 3
Classifier: Programming Language :: Python :: 3.5
Classifier: Programming Language :: Python :: 3.6
Classifier: Programming Language :: Python :: 3.7
Classifier: Programming Language :: Python :: 3.8
Classifier: Programming Language :: Python :: 3.9
Requires-Python: >=3.5, <4
License-File: LICENSE
Requires-Dist: simpy
Requires-Dist: tqdm
Requires-Dist: jsonschema
Requires-Dist: typer[all]
Requires-Dist: pandas
